another_fastapi_jwt_auth/__init__.py
another_fastapi_jwt_auth/auth_config.py
another_fastapi_jwt_auth/auth_jwt.py
another_fastapi_jwt_auth/config.py
another_fastapi_jwt_auth/exceptions.py
another_fastapi_jwt_auth-0.1.7.dist-info/METADATA
another_fastapi_jwt_auth-0.1.7.dist-info/WHEEL
another_fastapi_jwt_auth-0.1.7.dist-info/licenses/LICENSE
another_fastapi_jwt_auth-0.1.7.dist-info/RECORD
