Metadata-Version: 2.4
Name: another-fastapi-jwt-auth
Version: 0.1.7
Summary: Another iteration of fastapi-jwt-auth
License-File: LICENSE
Author: Nyoman Pradipta Dewantara
Author-email: nyomanpradipta120@gmail.com
Requires-Python: >=3.10,<4
Classifier: Environment :: Web Environment
Classifier: Intended Audience :: Developers
Classifier: License :: OSI Approved :: MIT License
Classifier: Operating System :: OS Independent
Classifier: Programming Language :: Python :: 3
Classifier: Programming Language :: Python :: 3.10
Classifier: Programming Language :: Python :: 3.11
Classifier: Programming Language :: Python :: 3.12
Classifier: Programming Language :: Python :: 3.13
Classifier: Programming Language :: Python :: 3.14
Classifier: Topic :: Internet :: WWW/HTTP :: Dynamic Content
Classifier: Topic :: Software Development :: Libraries :: Python Modules
Requires-Dist: PyJWT (>2)
Requires-Dist: fastapi (>=0.128.0)
Requires-Dist: pydantic (>=2,<3)
Project-URL: Homepage, https://github.com/delrey1/another-fastapi-jwt-auth
